LICENSE
MANIFEST.in
README.md
manual.md
manual.pdf
promod
promod-tk
setup.cfg
setup.py
theory.md
builder/__init__.py
builder/build_macrocomplex.py
builder/errors.py
builder/optimize.py
builder/superimpose.py
promod.egg-info/PKG-INFO
promod.egg-info/SOURCES.txt
promod.egg-info/dependency_links.txt
promod.egg-info/top_level.txt
scripts/pairpdbs.py
scripts/pdbsplit.py