Metadata-Version: 2.1
Name: promod
Version: 0.1.7
Summary: A macromolecular complex builder
Home-page: https://github.com/Fabian-RY/SBI-Python-project
Author: Fabián Robledo, Claudio Díaz
Author-email: fabian.robledo01@estudiant.upf.edu
License: MIT
Keywords: bioinformatics structural_bioinformatics protein complex builder modeler
Platform: UNKNOWN
Classifier: Programming Language :: Python :: 3
Classifier: License :: OSI Approved :: MIT License
Classifier: Operating System :: OS Independent
Requires-Python: >=3
